birds/__init__.py
birds/settings.py
birds/version.py
birds/data/__init__.py
birds/data/data_loader.py
birds/demo/__init__.py
birds/demo/demo_woe.py
birds/util/__init__.py
birds/util/model_helper/__init__.py
birds/util/model_helper/mono_woe_v1.py
pybirds/__init__.py
pybirds/settings.py
pybirds/version.py
pybirds/data/__init__.py
pybirds/data/credit_german.csv
pybirds/data/data_loader.py
pybirds/data/score_sample.csv
pybirds/demo/__init__.py
pybirds/demo/demo_mono_woe.py
pybirds/demo/demo_score_bin.py
pybirds/demo/demo_score_mapping.py
pybirds/demo/demo_woe.py
pybirds/util/__init__.py
pybirds/util/io_helper/__init__.py
pybirds/util/io_helper/file_helper.py
pybirds/util/model_helper/__init__.py
pybirds/util/model_helper/feature_selection.py
pybirds/util/model_helper/logistic_benchmark.py
pybirds/util/model_helper/mapping.py
pybirds/util/model_helper/mono_woe.py
pybirds/util/model_helper/mono_woe_v1.py
pybirds/util/model_helper/score_bin.py
pybirds/util/model_helper/score_mapping.py
pybirds-0.0.3.dist-info/METADATA
pybirds-0.0.3.dist-info/WHEEL
pybirds-0.0.3.dist-info/top_level.txt
pybirds-0.0.3.dist-info/RECORD
