Metadata-Version: 2.1
Name: pybirds
Version: 0.0.3
Summary: Business Intelligence Risk Data Science
Home-page: UNKNOWN
Author: Ouyang Ruofei
Author-email: rfouyang@gmail.com
License: UNKNOWN
Keywords: pybirds,birds
Platform: any
Classifier: Environment :: MacOS X
Classifier: Intended Audience :: Developers
Classifier: License :: OSI Approved :: MIT License
Classifier: Operating System :: OS Independent
Classifier: Programming Language :: Python :: 3.6
Classifier: Topic :: Software Development :: Libraries :: Python Modules
Requires-Python: >=3.6
Requires-Dist: numpy (==1.19.4)
Requires-Dist: scipy (==1.3.2)
Requires-Dist: pandas (==1.1.4)
Requires-Dist: statsmodels (==0.10.1)
Requires-Dist: matplotlib (==3.1.1)
Requires-Dist: seaborn (==0.11.0)
Requires-Dist: termcolor (==1.1.0)
Requires-Dist: python-dateutil (==2.8.1)
Requires-Dist: urllib3 (==1.25.8)
Requires-Dist: requests (==2.23.0)
Requires-Dist: oauthlib (==3.1.0)
Requires-Dist: pyparsing (==2.4.7)
Requires-Dist: tqdm (==4.43.0)
Requires-Dist: scikit-learn (==0.23.1)
Requires-Dist: scikit-optimize (==0.7.4)
Requires-Dist: scikit-plot (==0.3.7)
Requires-Dist: lightgbm (==2.2.3)
Requires-Dist: ipywidgets (==7.5.1)
Requires-Dist: joblib (==0.14.0)
Requires-Dist: pyarrow (==3.0.0)
Requires-Dist: simplejson
Requires-Dist: xlrd (==1.2.0)
Requires-Dist: psutil (==5.8.0)
